<?xml version="1.0" encoding="UTF-8" standalone="yes"?>
<prov:document xmlns:prov="http://www.w3.org/ns/prov#" xmlns:ns2="http://openprovenance.org/prov/extension#" xmlns:xsi="http://www.w3.org/2001/XMLSchema-instance" xmlns:xsd="http://www.w3.org/2001/XMLSchema" xmlns:pronaliz="http://www.pronaliz.yildiz.edu.tr">
<prov:activity prov:id="Process_5787">
	<prov:startTime>2011-10-13T00:51:25.000-04:00</prov:startTime>
	<prov:endTime>2011-10-13T00:51:25.000-04:00</prov:endTime>
</prov:activity>
<prov:entity prov:id="File_1447">
	<prov:value>Input</prov:value>
</prov:entity>
<prov:used>
	<prov:activity prov:ref="Process_5787"/>
	<prov:entity prov:ref="File_1447"/>
</prov:used>
<prov:entity prov:id="File_1449">
	<prov:value>Input</prov:value>
</prov:entity>
<prov:used>
	<prov:activity prov:ref="Process_5787"/>
	<prov:entity prov:ref="File_1449"/>
</prov:used>
<prov:entity prov:id="File_1451">
	<prov:value>Input</prov:value>
</prov:entity>
<prov:used>
	<prov:activity prov:ref="Process_5787"/>
	<prov:entity prov:ref="File_1451"/>
</prov:used>
<prov:entity prov:id="File_1453">
	<prov:value>Input</prov:value>
</prov:entity>
<prov:used>
	<prov:activity prov:ref="Process_5787"/>
	<prov:entity prov:ref="File_1453"/>
</prov:used>
<prov:entity prov:id="File_1456">
	<prov:value>Input</prov:value>
</prov:entity>
<prov:used>
	<prov:activity prov:ref="Process_5787"/>
	<prov:entity prov:ref="File_1456"/>
</prov:used>
<prov:entity prov:id="File_1457">
	<prov:value>Input</prov:value>
</prov:entity>
<prov:used>
	<prov:activity prov:ref="Process_5787"/>
	<prov:entity prov:ref="File_1457"/>
</prov:used>
<prov:entity prov:id="File_1459">
	<prov:value>Input</prov:value>
</prov:entity>
<prov:used>
	<prov:activity prov:ref="Process_5787"/>
	<prov:entity prov:ref="File_1459"/>
</prov:used>
<prov:entity prov:id="File_1461">
	<prov:value>Input</prov:value>
</prov:entity>
<prov:used>
	<prov:activity prov:ref="Process_5787"/>
	<prov:entity prov:ref="File_1461"/>
</prov:used>
<prov:entity prov:id="File_1463">
	<prov:value>Input</prov:value>
</prov:entity>
<prov:used>
	<prov:activity prov:ref="Process_5787"/>
	<prov:entity prov:ref="File_1463"/>
</prov:used>
<prov:entity prov:id="File_1465">
	<prov:value>Input</prov:value>
</prov:entity>
<prov:used>
	<prov:activity prov:ref="Process_5787"/>
	<prov:entity prov:ref="File_1465"/>
</prov:used>
<prov:entity prov:id="File_1467">
	<prov:value>Input</prov:value>
</prov:entity>
<prov:used>
	<prov:activity prov:ref="Process_5787"/>
	<prov:entity prov:ref="File_1467"/>
</prov:used>
<prov:entity prov:id="File_1470">
	<prov:value>Input</prov:value>
</prov:entity>
<prov:used>
	<prov:activity prov:ref="Process_5787"/>
	<prov:entity prov:ref="File_1470"/>
</prov:used>
<prov:entity prov:id="File_1471">
	<prov:value>Input</prov:value>
</prov:entity>
<prov:used>
	<prov:activity prov:ref="Process_5787"/>
	<prov:entity prov:ref="File_1471"/>
</prov:used>
<prov:entity prov:id="File_1473">
	<prov:value>Input</prov:value>
</prov:entity>
<prov:used>
	<prov:activity prov:ref="Process_5787"/>
	<prov:entity prov:ref="File_1473"/>
</prov:used>
<prov:entity prov:id="File_1475">
	<prov:value>Input</prov:value>
</prov:entity>
<prov:used>
	<prov:activity prov:ref="Process_5787"/>
	<prov:entity prov:ref="File_1475"/>
</prov:used>
<prov:entity prov:id="File_1477">
	<prov:value>Input</prov:value>
</prov:entity>
<prov:used>
	<prov:activity prov:ref="Process_5787"/>
	<prov:entity prov:ref="File_1477"/>
</prov:used>
<prov:entity prov:id="File_1479">
	<prov:value>Input</prov:value>
</prov:entity>
<prov:used>
	<prov:activity prov:ref="Process_5787"/>
	<prov:entity prov:ref="File_1479"/>
</prov:used>
<prov:entity prov:id="File_1481">
	<prov:value>Input</prov:value>
</prov:entity>
<prov:used>
	<prov:activity prov:ref="Process_5787"/>
	<prov:entity prov:ref="File_1481"/>
</prov:used>
<prov:entity prov:id="File_1484">
	<prov:value>Input</prov:value>
</prov:entity>
<prov:used>
	<prov:activity prov:ref="Process_5787"/>
	<prov:entity prov:ref="File_1484"/>
</prov:used>
<prov:entity prov:id="File_1485">
	<prov:value>Input</prov:value>
</prov:entity>
<prov:used>
	<prov:activity prov:ref="Process_5787"/>
	<prov:entity prov:ref="File_1485"/>
</prov:used>
<prov:entity prov:id="File_1488">
	<prov:value>Input</prov:value>
</prov:entity>
<prov:used>
	<prov:activity prov:ref="Process_5787"/>
	<prov:entity prov:ref="File_1488"/>
</prov:used>
<prov:entity prov:id="File_1489">
	<prov:value>Input</prov:value>
</prov:entity>
<prov:used>
	<prov:activity prov:ref="Process_5787"/>
	<prov:entity prov:ref="File_1489"/>
</prov:used>
<prov:entity prov:id="File_1491">
	<prov:value>Input</prov:value>
</prov:entity>
<prov:used>
	<prov:activity prov:ref="Process_5787"/>
	<prov:entity prov:ref="File_1491"/>
</prov:used>
<prov:entity prov:id="File_1493">
	<prov:value>Input</prov:value>
</prov:entity>
<prov:used>
	<prov:activity prov:ref="Process_5787"/>
	<prov:entity prov:ref="File_1493"/>
</prov:used>
<prov:entity prov:id="File_1495">
	<prov:value>Input</prov:value>
</prov:entity>
<prov:used>
	<prov:activity prov:ref="Process_5787"/>
	<prov:entity prov:ref="File_1495"/>
</prov:used>
<prov:entity prov:id="File_1497">
	<prov:value>Input</prov:value>
</prov:entity>
<prov:used>
	<prov:activity prov:ref="Process_5787"/>
	<prov:entity prov:ref="File_1497"/>
</prov:used>
<prov:entity prov:id="File_1499">
	<prov:value>Input</prov:value>
</prov:entity>
<prov:used>
	<prov:activity prov:ref="Process_5787"/>
	<prov:entity prov:ref="File_1499"/>
</prov:used>
<prov:entity prov:id="File_1501">
	<prov:value>Input</prov:value>
</prov:entity>
<prov:used>
	<prov:activity prov:ref="Process_5787"/>
	<prov:entity prov:ref="File_1501"/>
</prov:used>
<prov:entity prov:id="File_1504">
	<prov:value>Input</prov:value>
</prov:entity>
<prov:used>
	<prov:activity prov:ref="Process_5787"/>
	<prov:entity prov:ref="File_1504"/>
</prov:used>
<prov:entity prov:id="File_1505">
	<prov:value>Input</prov:value>
</prov:entity>
<prov:used>
	<prov:activity prov:ref="Process_5787"/>
	<prov:entity prov:ref="File_1505"/>
</prov:used>
<prov:entity prov:id="File_4399">
	<prov:value>Input</prov:value>
</prov:entity>
<prov:used>
	<prov:activity prov:ref="Process_5787"/>
	<prov:entity prov:ref="File_4399"/>
</prov:used>
<prov:activity prov:id="Process_5789">
	<prov:startTime>2011-10-13T00:01:37.000-04:00</prov:startTime>
	<prov:endTime>2011-10-13T00:01:35.000-04:00</prov:endTime>
</prov:activity>
<prov:entity prov:id="File_4414">
	<prov:value>Input</prov:value>
</prov:entity>
<prov:used>
	<prov:activity prov:ref="Process_5789"/>
	<prov:entity prov:ref="File_4414"/>
</prov:used>
<prov:entity prov:id="File_4415">
	<prov:value>Input</prov:value>
</prov:entity>
<prov:used>
	<prov:activity prov:ref="Process_5789"/>
	<prov:entity prov:ref="File_4415"/>
</prov:used>
<prov:entity prov:id="File_4416">
	<prov:value>Input</prov:value>
</prov:entity>
<prov:used>
	<prov:activity prov:ref="Process_5789"/>
	<prov:entity prov:ref="File_4416"/>
</prov:used>
<prov:activity prov:id="Process_5790">
	<prov:startTime>2011-10-13T00:01:40.000-04:00</prov:startTime>
	<prov:endTime>2011-10-13T00:01:40.000-04:00</prov:endTime>
</prov:activity>
<prov:entity prov:id="File_4420">
	<prov:value>Input</prov:value>
</prov:entity>
<prov:used>
	<prov:activity prov:ref="Process_5790"/>
	<prov:entity prov:ref="File_4420"/>
</prov:used>
<prov:entity prov:id="File_4421">
	<prov:value>Input</prov:value>
</prov:entity>
<prov:used>
	<prov:activity prov:ref="Process_5790"/>
	<prov:entity prov:ref="File_4421"/>
</prov:used>
<prov:entity prov:id="File_4422">
	<prov:value>Input</prov:value>
</prov:entity>
<prov:used>
	<prov:activity prov:ref="Process_5790"/>
	<prov:entity prov:ref="File_4422"/>
</prov:used>
<prov:entity prov:id="File_4423">
	<prov:value>Input</prov:value>
</prov:entity>
<prov:used>
	<prov:activity prov:ref="Process_5790"/>
	<prov:entity prov:ref="File_4423"/>
</prov:used>
<prov:entity prov:id="File_4424">
	<prov:value>Input</prov:value>
</prov:entity>
<prov:used>
	<prov:activity prov:ref="Process_5790"/>
	<prov:entity prov:ref="File_4424"/>
</prov:used>
<prov:entity prov:id="File_4425">
	<prov:value>Input</prov:value>
</prov:entity>
<prov:used>
	<prov:activity prov:ref="Process_5790"/>
	<prov:entity prov:ref="File_4425"/>
</prov:used>
<prov:entity prov:id="File_4426">
	<prov:value>Input</prov:value>
</prov:entity>
<prov:used>
	<prov:activity prov:ref="Process_5790"/>
	<prov:entity prov:ref="File_4426"/>
</prov:used>
<prov:entity prov:id="File_4427">
	<prov:value>Input</prov:value>
</prov:entity>
<prov:used>
	<prov:activity prov:ref="Process_5790"/>
	<prov:entity prov:ref="File_4427"/>
</prov:used>
<prov:entity prov:id="File_4428">
	<prov:value>Input</prov:value>
</prov:entity>
<prov:used>
	<prov:activity prov:ref="Process_5790"/>
	<prov:entity prov:ref="File_4428"/>
</prov:used>
<prov:entity prov:id="File_4429">
	<prov:value>Input</prov:value>
</prov:entity>
<prov:used>
	<prov:activity prov:ref="Process_5790"/>
	<prov:entity prov:ref="File_4429"/>
</prov:used>
<prov:wasDerivedFrom>
	<prov:generatedEntity prov:ref="File_4414"/>
	<prov:usedEntity prov:ref="File_1447"/>
</prov:wasDerivedFrom>
<prov:wasDerivedFrom>
	<prov:generatedEntity prov:ref="File_4414"/>
	<prov:usedEntity prov:ref="File_1449"/>
</prov:wasDerivedFrom>
<prov:wasDerivedFrom>
	<prov:generatedEntity prov:ref="File_4414"/>
	<prov:usedEntity prov:ref="File_1451"/>
</prov:wasDerivedFrom>
<prov:wasDerivedFrom>
	<prov:generatedEntity prov:ref="File_4414"/>
	<prov:usedEntity prov:ref="File_1453"/>
</prov:wasDerivedFrom>
<prov:wasDerivedFrom>
	<prov:generatedEntity prov:ref="File_4414"/>
	<prov:usedEntity prov:ref="File_1456"/>
</prov:wasDerivedFrom>
<prov:wasDerivedFrom>
	<prov:generatedEntity prov:ref="File_4414"/>
	<prov:usedEntity prov:ref="File_1457"/>
</prov:wasDerivedFrom>
<prov:wasDerivedFrom>
	<prov:generatedEntity prov:ref="File_4414"/>
	<prov:usedEntity prov:ref="File_1459"/>
</prov:wasDerivedFrom>
<prov:wasDerivedFrom>
	<prov:generatedEntity prov:ref="File_4414"/>
	<prov:usedEntity prov:ref="File_1461"/>
</prov:wasDerivedFrom>
<prov:wasDerivedFrom>
	<prov:generatedEntity prov:ref="File_4414"/>
	<prov:usedEntity prov:ref="File_1475"/>
</prov:wasDerivedFrom>
<prov:wasDerivedFrom>
	<prov:generatedEntity prov:ref="File_4414"/>
	<prov:usedEntity prov:ref="File_1463"/>
</prov:wasDerivedFrom>
<prov:wasDerivedFrom>
	<prov:generatedEntity prov:ref="File_4414"/>
	<prov:usedEntity prov:ref="File_1477"/>
</prov:wasDerivedFrom>
<prov:wasDerivedFrom>
	<prov:generatedEntity prov:ref="File_4414"/>
	<prov:usedEntity prov:ref="File_1465"/>
</prov:wasDerivedFrom>
<prov:wasDerivedFrom>
	<prov:generatedEntity prov:ref="File_4414"/>
	<prov:usedEntity prov:ref="File_1479"/>
</prov:wasDerivedFrom>
<prov:wasDerivedFrom>
	<prov:generatedEntity prov:ref="File_4414"/>
	<prov:usedEntity prov:ref="File_1467"/>
</prov:wasDerivedFrom>
<prov:wasDerivedFrom>
	<prov:generatedEntity prov:ref="File_4414"/>
	<prov:usedEntity prov:ref="File_1481"/>
</prov:wasDerivedFrom>
<prov:wasDerivedFrom>
	<prov:generatedEntity prov:ref="File_4414"/>
	<prov:usedEntity prov:ref="File_1470"/>
</prov:wasDerivedFrom>
<prov:wasDerivedFrom>
	<prov:generatedEntity prov:ref="File_4414"/>
	<prov:usedEntity prov:ref="File_1484"/>
</prov:wasDerivedFrom>
<prov:wasDerivedFrom>
	<prov:generatedEntity prov:ref="File_4414"/>
	<prov:usedEntity prov:ref="File_1471"/>
</prov:wasDerivedFrom>
<prov:wasDerivedFrom>
	<prov:generatedEntity prov:ref="File_4414"/>
	<prov:usedEntity prov:ref="File_1485"/>
</prov:wasDerivedFrom>
<prov:wasDerivedFrom>
	<prov:generatedEntity prov:ref="File_4414"/>
	<prov:usedEntity prov:ref="File_1473"/>
</prov:wasDerivedFrom>
<prov:wasDerivedFrom>
	<prov:generatedEntity prov:ref="File_4414"/>
	<prov:usedEntity prov:ref="File_1488"/>
</prov:wasDerivedFrom>
<prov:wasDerivedFrom>
	<prov:generatedEntity prov:ref="File_4414"/>
	<prov:usedEntity prov:ref="File_1489"/>
</prov:wasDerivedFrom>
<prov:wasDerivedFrom>
	<prov:generatedEntity prov:ref="File_4414"/>
	<prov:usedEntity prov:ref="File_1491"/>
</prov:wasDerivedFrom>
<prov:wasDerivedFrom>
	<prov:generatedEntity prov:ref="File_4414"/>
	<prov:usedEntity prov:ref="File_1493"/>
</prov:wasDerivedFrom>
<prov:wasDerivedFrom>
	<prov:generatedEntity prov:ref="File_4414"/>
	<prov:usedEntity prov:ref="File_1495"/>
</prov:wasDerivedFrom>
<prov:wasDerivedFrom>
	<prov:generatedEntity prov:ref="File_4414"/>
	<prov:usedEntity prov:ref="File_1497"/>
</prov:wasDerivedFrom>
<prov:wasDerivedFrom>
	<prov:generatedEntity prov:ref="File_4414"/>
	<prov:usedEntity prov:ref="File_1499"/>
</prov:wasDerivedFrom>
<prov:wasDerivedFrom>
	<prov:generatedEntity prov:ref="File_4414"/>
	<prov:usedEntity prov:ref="File_1501"/>
</prov:wasDerivedFrom>
<prov:wasDerivedFrom>
	<prov:generatedEntity prov:ref="File_4414"/>
	<prov:usedEntity prov:ref="File_1504"/>
</prov:wasDerivedFrom>
<prov:wasDerivedFrom>
	<prov:generatedEntity prov:ref="File_4414"/>
	<prov:usedEntity prov:ref="File_1505"/>
</prov:wasDerivedFrom>
<prov:wasDerivedFrom>
	<prov:generatedEntity prov:ref="File_4414"/>
	<prov:usedEntity prov:ref="File_4399"/>
</prov:wasDerivedFrom>
<prov:wasDerivedFrom>
	<prov:generatedEntity prov:ref="File_4415"/>
	<prov:usedEntity prov:ref="File_1447"/>
</prov:wasDerivedFrom>
<prov:wasDerivedFrom>
	<prov:generatedEntity prov:ref="File_4415"/>
	<prov:usedEntity prov:ref="File_1449"/>
</prov:wasDerivedFrom>
<prov:wasDerivedFrom>
	<prov:generatedEntity prov:ref="File_4415"/>
	<prov:usedEntity prov:ref="File_1451"/>
</prov:wasDerivedFrom>
<prov:wasDerivedFrom>
	<prov:generatedEntity prov:ref="File_4415"/>
	<prov:usedEntity prov:ref="File_1453"/>
</prov:wasDerivedFrom>
<prov:wasDerivedFrom>
	<prov:generatedEntity prov:ref="File_4415"/>
	<prov:usedEntity prov:ref="File_1456"/>
</prov:wasDerivedFrom>
<prov:wasDerivedFrom>
	<prov:generatedEntity prov:ref="File_4415"/>
	<prov:usedEntity prov:ref="File_1457"/>
</prov:wasDerivedFrom>
<prov:wasDerivedFrom>
	<prov:generatedEntity prov:ref="File_4415"/>
	<prov:usedEntity prov:ref="File_1459"/>
</prov:wasDerivedFrom>
<prov:wasDerivedFrom>
	<prov:generatedEntity prov:ref="File_4415"/>
	<prov:usedEntity prov:ref="File_1461"/>
</prov:wasDerivedFrom>
<prov:wasDerivedFrom>
	<prov:generatedEntity prov:ref="File_4415"/>
	<prov:usedEntity prov:ref="File_1475"/>
</prov:wasDerivedFrom>
<prov:wasDerivedFrom>
	<prov:generatedEntity prov:ref="File_4415"/>
	<prov:usedEntity prov:ref="File_1463"/>
</prov:wasDerivedFrom>
<prov:wasDerivedFrom>
	<prov:generatedEntity prov:ref="File_4415"/>
	<prov:usedEntity prov:ref="File_1477"/>
</prov:wasDerivedFrom>
<prov:wasDerivedFrom>
	<prov:generatedEntity prov:ref="File_4415"/>
	<prov:usedEntity prov:ref="File_1465"/>
</prov:wasDerivedFrom>
<prov:wasDerivedFrom>
	<prov:generatedEntity prov:ref="File_4415"/>
	<prov:usedEntity prov:ref="File_1479"/>
</prov:wasDerivedFrom>
<prov:wasDerivedFrom>
	<prov:generatedEntity prov:ref="File_4415"/>
	<prov:usedEntity prov:ref="File_1467"/>
</prov:wasDerivedFrom>
<prov:wasDerivedFrom>
	<prov:generatedEntity prov:ref="File_4415"/>
	<prov:usedEntity prov:ref="File_1481"/>
</prov:wasDerivedFrom>
<prov:wasDerivedFrom>
	<prov:generatedEntity prov:ref="File_4415"/>
	<prov:usedEntity prov:ref="File_1470"/>
</prov:wasDerivedFrom>
<prov:wasDerivedFrom>
	<prov:generatedEntity prov:ref="File_4415"/>
	<prov:usedEntity prov:ref="File_1484"/>
</prov:wasDerivedFrom>
<prov:wasDerivedFrom>
	<prov:generatedEntity prov:ref="File_4415"/>
	<prov:usedEntity prov:ref="File_1471"/>
</prov:wasDerivedFrom>
<prov:wasDerivedFrom>
	<prov:generatedEntity prov:ref="File_4415"/>
	<prov:usedEntity prov:ref="File_1485"/>
</prov:wasDerivedFrom>
<prov:wasDerivedFrom>
	<prov:generatedEntity prov:ref="File_4415"/>
	<prov:usedEntity prov:ref="File_1473"/>
</prov:wasDerivedFrom>
<prov:wasDerivedFrom>
	<prov:generatedEntity prov:ref="File_4415"/>
	<prov:usedEntity prov:ref="File_1488"/>
</prov:wasDerivedFrom>
<prov:wasDerivedFrom>
	<prov:generatedEntity prov:ref="File_4415"/>
	<prov:usedEntity prov:ref="File_1489"/>
</prov:wasDerivedFrom>
<prov:wasDerivedFrom>
	<prov:generatedEntity prov:ref="File_4415"/>
	<prov:usedEntity prov:ref="File_1491"/>
</prov:wasDerivedFrom>
<prov:wasDerivedFrom>
	<prov:generatedEntity prov:ref="File_4415"/>
	<prov:usedEntity prov:ref="File_1493"/>
</prov:wasDerivedFrom>
<prov:wasDerivedFrom>
	<prov:generatedEntity prov:ref="File_4415"/>
	<prov:usedEntity prov:ref="File_1495"/>
</prov:wasDerivedFrom>
<prov:wasDerivedFrom>
	<prov:generatedEntity prov:ref="File_4415"/>
	<prov:usedEntity prov:ref="File_1497"/>
</prov:wasDerivedFrom>
<prov:wasDerivedFrom>
	<prov:generatedEntity prov:ref="File_4415"/>
	<prov:usedEntity prov:ref="File_1499"/>
</prov:wasDerivedFrom>
<prov:wasDerivedFrom>
	<prov:generatedEntity prov:ref="File_4415"/>
	<prov:usedEntity prov:ref="File_1501"/>
</prov:wasDerivedFrom>
<prov:wasDerivedFrom>
	<prov:generatedEntity prov:ref="File_4415"/>
	<prov:usedEntity prov:ref="File_1504"/>
</prov:wasDerivedFrom>
<prov:wasDerivedFrom>
	<prov:generatedEntity prov:ref="File_4415"/>
	<prov:usedEntity prov:ref="File_1505"/>
</prov:wasDerivedFrom>
<prov:wasDerivedFrom>
	<prov:generatedEntity prov:ref="File_4415"/>
	<prov:usedEntity prov:ref="File_4399"/>
</prov:wasDerivedFrom>
<prov:wasDerivedFrom>
	<prov:generatedEntity prov:ref="File_4416"/>
	<prov:usedEntity prov:ref="File_1447"/>
</prov:wasDerivedFrom>
<prov:wasDerivedFrom>
	<prov:generatedEntity prov:ref="File_4416"/>
	<prov:usedEntity prov:ref="File_1449"/>
</prov:wasDerivedFrom>
<prov:wasDerivedFrom>
	<prov:generatedEntity prov:ref="File_4416"/>
	<prov:usedEntity prov:ref="File_1451"/>
</prov:wasDerivedFrom>
<prov:wasDerivedFrom>
	<prov:generatedEntity prov:ref="File_4416"/>
	<prov:usedEntity prov:ref="File_1453"/>
</prov:wasDerivedFrom>
<prov:wasDerivedFrom>
	<prov:generatedEntity prov:ref="File_4416"/>
	<prov:usedEntity prov:ref="File_1456"/>
</prov:wasDerivedFrom>
<prov:wasDerivedFrom>
	<prov:generatedEntity prov:ref="File_4416"/>
	<prov:usedEntity prov:ref="File_1457"/>
</prov:wasDerivedFrom>
<prov:wasDerivedFrom>
	<prov:generatedEntity prov:ref="File_4416"/>
	<prov:usedEntity prov:ref="File_1459"/>
</prov:wasDerivedFrom>
<prov:wasDerivedFrom>
	<prov:generatedEntity prov:ref="File_4416"/>
	<prov:usedEntity prov:ref="File_1461"/>
</prov:wasDerivedFrom>
<prov:wasDerivedFrom>
	<prov:generatedEntity prov:ref="File_4416"/>
	<prov:usedEntity prov:ref="File_1475"/>
</prov:wasDerivedFrom>
<prov:wasDerivedFrom>
	<prov:generatedEntity prov:ref="File_4416"/>
	<prov:usedEntity prov:ref="File_1463"/>
</prov:wasDerivedFrom>
<prov:wasDerivedFrom>
	<prov:generatedEntity prov:ref="File_4416"/>
	<prov:usedEntity prov:ref="File_1477"/>
</prov:wasDerivedFrom>
<prov:wasDerivedFrom>
	<prov:generatedEntity prov:ref="File_4416"/>
	<prov:usedEntity prov:ref="File_1465"/>
</prov:wasDerivedFrom>
<prov:wasDerivedFrom>
	<prov:generatedEntity prov:ref="File_4416"/>
	<prov:usedEntity prov:ref="File_1479"/>
</prov:wasDerivedFrom>
<prov:wasDerivedFrom>
	<prov:generatedEntity prov:ref="File_4416"/>
	<prov:usedEntity prov:ref="File_1467"/>
</prov:wasDerivedFrom>
<prov:wasDerivedFrom>
	<prov:generatedEntity prov:ref="File_4416"/>
	<prov:usedEntity prov:ref="File_1481"/>
</prov:wasDerivedFrom>
<prov:wasDerivedFrom>
	<prov:generatedEntity prov:ref="File_4416"/>
	<prov:usedEntity prov:ref="File_1470"/>
</prov:wasDerivedFrom>
<prov:wasDerivedFrom>
	<prov:generatedEntity prov:ref="File_4416"/>
	<prov:usedEntity prov:ref="File_1484"/>
</prov:wasDerivedFrom>
<prov:wasDerivedFrom>
	<prov:generatedEntity prov:ref="File_4416"/>
	<prov:usedEntity prov:ref="File_1471"/>
</prov:wasDerivedFrom>
<prov:wasDerivedFrom>
	<prov:generatedEntity prov:ref="File_4416"/>
	<prov:usedEntity prov:ref="File_1485"/>
</prov:wasDerivedFrom>
<prov:wasDerivedFrom>
	<prov:generatedEntity prov:ref="File_4416"/>
	<prov:usedEntity prov:ref="File_1473"/>
</prov:wasDerivedFrom>
<prov:wasDerivedFrom>
	<prov:generatedEntity prov:ref="File_4416"/>
	<prov:usedEntity prov:ref="File_1488"/>
</prov:wasDerivedFrom>
<prov:wasDerivedFrom>
	<prov:generatedEntity prov:ref="File_4416"/>
	<prov:usedEntity prov:ref="File_1489"/>
</prov:wasDerivedFrom>
<prov:wasDerivedFrom>
	<prov:generatedEntity prov:ref="File_4416"/>
	<prov:usedEntity prov:ref="File_1491"/>
</prov:wasDerivedFrom>
<prov:wasDerivedFrom>
	<prov:generatedEntity prov:ref="File_4416"/>
	<prov:usedEntity prov:ref="File_1493"/>
</prov:wasDerivedFrom>
<prov:wasDerivedFrom>
	<prov:generatedEntity prov:ref="File_4416"/>
	<prov:usedEntity prov:ref="File_1495"/>
</prov:wasDerivedFrom>
<prov:wasDerivedFrom>
	<prov:generatedEntity prov:ref="File_4416"/>
	<prov:usedEntity prov:ref="File_1497"/>
</prov:wasDerivedFrom>
<prov:wasDerivedFrom>
	<prov:generatedEntity prov:ref="File_4416"/>
	<prov:usedEntity prov:ref="File_1499"/>
</prov:wasDerivedFrom>
<prov:wasDerivedFrom>
	<prov:generatedEntity prov:ref="File_4416"/>
	<prov:usedEntity prov:ref="File_1501"/>
</prov:wasDerivedFrom>
<prov:wasDerivedFrom>
	<prov:generatedEntity prov:ref="File_4416"/>
	<prov:usedEntity prov:ref="File_1504"/>
</prov:wasDerivedFrom>
<prov:wasDerivedFrom>
	<prov:generatedEntity prov:ref="File_4416"/>
	<prov:usedEntity prov:ref="File_1505"/>
</prov:wasDerivedFrom>
<prov:wasDerivedFrom>
	<prov:generatedEntity prov:ref="File_4416"/>
	<prov:usedEntity prov:ref="File_4399"/>
</prov:wasDerivedFrom>
<prov:entity prov:id="File_4417">
</prov:entity>
<prov:wasDerivedFrom>
	<prov:generatedEntity prov:ref="File_4417"/>
	<prov:usedEntity prov:ref="File_4420"/>
</prov:wasDerivedFrom>
<prov:wasDerivedFrom>
	<prov:generatedEntity prov:ref="File_4417"/>
	<prov:usedEntity prov:ref="File_4421"/>
</prov:wasDerivedFrom>
<prov:wasDerivedFrom>
	<prov:generatedEntity prov:ref="File_4417"/>
	<prov:usedEntity prov:ref="File_4422"/>
</prov:wasDerivedFrom>
<prov:wasDerivedFrom>
	<prov:generatedEntity prov:ref="File_4417"/>
	<prov:usedEntity prov:ref="File_4423"/>
</prov:wasDerivedFrom>
<prov:wasDerivedFrom>
	<prov:generatedEntity prov:ref="File_4417"/>
	<prov:usedEntity prov:ref="File_4424"/>
</prov:wasDerivedFrom>
<prov:wasDerivedFrom>
	<prov:generatedEntity prov:ref="File_4417"/>
	<prov:usedEntity prov:ref="File_4425"/>
</prov:wasDerivedFrom>
<prov:wasDerivedFrom>
	<prov:generatedEntity prov:ref="File_4417"/>
	<prov:usedEntity prov:ref="File_4426"/>
</prov:wasDerivedFrom>
<prov:wasDerivedFrom>
	<prov:generatedEntity prov:ref="File_4417"/>
	<prov:usedEntity prov:ref="File_4427"/>
</prov:wasDerivedFrom>
<prov:wasDerivedFrom>
	<prov:generatedEntity prov:ref="File_4417"/>
	<prov:usedEntity prov:ref="File_4428"/>
</prov:wasDerivedFrom>
<prov:wasDerivedFrom>
	<prov:generatedEntity prov:ref="File_4417"/>
	<prov:usedEntity prov:ref="File_4429"/>
</prov:wasDerivedFrom>
<prov:entity prov:id="File_4418">
</prov:entity>
<prov:wasDerivedFrom>
	<prov:generatedEntity prov:ref="File_4418"/>
	<prov:usedEntity prov:ref="File_4420"/>
</prov:wasDerivedFrom>
<prov:wasDerivedFrom>
	<prov:generatedEntity prov:ref="File_4418"/>
	<prov:usedEntity prov:ref="File_4421"/>
</prov:wasDerivedFrom>
<prov:wasDerivedFrom>
	<prov:generatedEntity prov:ref="File_4418"/>
	<prov:usedEntity prov:ref="File_4422"/>
</prov:wasDerivedFrom>
<prov:wasDerivedFrom>
	<prov:generatedEntity prov:ref="File_4418"/>
	<prov:usedEntity prov:ref="File_4423"/>
</prov:wasDerivedFrom>
<prov:wasDerivedFrom>
	<prov:generatedEntity prov:ref="File_4418"/>
	<prov:usedEntity prov:ref="File_4424"/>
</prov:wasDerivedFrom>
<prov:wasDerivedFrom>
	<prov:generatedEntity prov:ref="File_4418"/>
	<prov:usedEntity prov:ref="File_4425"/>
</prov:wasDerivedFrom>
<prov:wasDerivedFrom>
	<prov:generatedEntity prov:ref="File_4418"/>
	<prov:usedEntity prov:ref="File_4426"/>
</prov:wasDerivedFrom>
<prov:wasDerivedFrom>
	<prov:generatedEntity prov:ref="File_4418"/>
	<prov:usedEntity prov:ref="File_4427"/>
</prov:wasDerivedFrom>
<prov:wasDerivedFrom>
	<prov:generatedEntity prov:ref="File_4418"/>
	<prov:usedEntity prov:ref="File_4428"/>
</prov:wasDerivedFrom>
<prov:wasDerivedFrom>
	<prov:generatedEntity prov:ref="File_4418"/>
	<prov:usedEntity prov:ref="File_4429"/>
</prov:wasDerivedFrom>
<prov:entity prov:id="File_4419">
</prov:entity>
<prov:wasDerivedFrom>
	<prov:generatedEntity prov:ref="File_4419"/>
	<prov:usedEntity prov:ref="File_4420"/>
</prov:wasDerivedFrom>
<prov:wasDerivedFrom>
	<prov:generatedEntity prov:ref="File_4419"/>
	<prov:usedEntity prov:ref="File_4421"/>
</prov:wasDerivedFrom>
<prov:wasDerivedFrom>
	<prov:generatedEntity prov:ref="File_4419"/>
	<prov:usedEntity prov:ref="File_4422"/>
</prov:wasDerivedFrom>
<prov:wasDerivedFrom>
	<prov:generatedEntity prov:ref="File_4419"/>
	<prov:usedEntity prov:ref="File_4423"/>
</prov:wasDerivedFrom>
<prov:wasDerivedFrom>
	<prov:generatedEntity prov:ref="File_4419"/>
	<prov:usedEntity prov:ref="File_4424"/>
</prov:wasDerivedFrom>
<prov:wasDerivedFrom>
	<prov:generatedEntity prov:ref="File_4419"/>
	<prov:usedEntity prov:ref="File_4425"/>
</prov:wasDerivedFrom>
<prov:wasDerivedFrom>
	<prov:generatedEntity prov:ref="File_4419"/>
	<prov:usedEntity prov:ref="File_4426"/>
</prov:wasDerivedFrom>
<prov:wasDerivedFrom>
	<prov:generatedEntity prov:ref="File_4419"/>
	<prov:usedEntity prov:ref="File_4427"/>
</prov:wasDerivedFrom>
<prov:wasDerivedFrom>
	<prov:generatedEntity prov:ref="File_4419"/>
	<prov:usedEntity prov:ref="File_4428"/>
</prov:wasDerivedFrom>
<prov:wasDerivedFrom>
	<prov:generatedEntity prov:ref="File_4419"/>
	<prov:usedEntity prov:ref="File_4429"/>
</prov:wasDerivedFrom>
<prov:wasInformedBy>
	<prov:informed prov:ref="Process_5789"/>
	<prov:informant prov:ref="Process_5787"/>
</prov:wasInformedBy>
<prov:wasInformedBy>
	<prov:informed prov:ref="Process_5789"/>
	<prov:informant prov:ref="Process_5787"/>
</prov:wasInformedBy>
<prov:wasInformedBy>
	<prov:informed prov:ref="Process_5789"/>
	<prov:informant prov:ref="Process_5787"/>
</prov:wasInformedBy>
<prov:activity prov:id="Process_5788">
	<prov:startTime>2011-10-13T00:51:35.000-04:00</prov:startTime>
	<prov:endTime>2011-10-13T00:51:35.000-04:00</prov:endTime>
</prov:activity>
<prov:wasInformedBy>
	<prov:informed prov:ref="Process_5787"/>
	<prov:informant prov:ref="Process_5788"/>
</prov:wasInformedBy>
<prov:wasInformedBy>
	<prov:informed prov:ref="Process_5789"/>
	<prov:informant prov:ref="Process_5788"/>
</prov:wasInformedBy>
<prov:wasInformedBy>
	<prov:informed prov:ref="Process_5790"/>
	<prov:informant prov:ref="Process_5788"/>
</prov:wasInformedBy>
<prov:wasGeneratedBy>
	<prov:entity prov:ref="File_4414"/>
	<prov:activity prov:ref="Process_5787"/>
	<prov:role>Output</prov:role>
</prov:wasGeneratedBy>
<prov:wasGeneratedBy>
	<prov:entity prov:ref="File_4415"/>
	<prov:activity prov:ref="Process_5787"/>
	<prov:role>Output</prov:role>
</prov:wasGeneratedBy>
<prov:wasGeneratedBy>
	<prov:entity prov:ref="File_4416"/>
	<prov:activity prov:ref="Process_5787"/>
	<prov:role>Output</prov:role>
</prov:wasGeneratedBy>
<prov:wasGeneratedBy>
	<prov:entity prov:ref="File_4417"/>
	<prov:activity prov:ref="Process_5790"/>
	<prov:role>Output</prov:role>
</prov:wasGeneratedBy>
<prov:wasGeneratedBy>
	<prov:entity prov:ref="File_4418"/>
	<prov:activity prov:ref="Process_5790"/>
	<prov:role>Output</prov:role>
</prov:wasGeneratedBy>
<prov:wasGeneratedBy>
	<prov:entity prov:ref="File_4419"/>
	<prov:activity prov:ref="Process_5790"/>
	<prov:role>Output</prov:role>
</prov:wasGeneratedBy>
</prov:document>