<?xml version="1.0" encoding="UTF-8" standalone="yes"?>
<prov:document xmlns:prov="http://www.w3.org/ns/prov#" xmlns:ns2="http://openprovenance.org/prov/extension#" xmlns:xsi="http://www.w3.org/2001/XMLSchema-instance" xmlns:xsd="http://www.w3.org/2001/XMLSchema" xmlns:pronaliz="http://www.pronaliz.yildiz.edu.tr">
<prov:activity prov:id="Process_5763">
	<prov:startTime>2011-10-12T00:33:18.000-04:00</prov:startTime>
	<prov:endTime>2011-10-12T00:33:18.000-04:00</prov:endTime>
</prov:activity>
<prov:entity prov:id="File_1103">
	<prov:value>Input</prov:value>
</prov:entity>
<prov:used>
	<prov:activity prov:ref="Process_5763"/>
	<prov:entity prov:ref="File_1103"/>
</prov:used>
<prov:entity prov:id="File_1105">
	<prov:value>Input</prov:value>
</prov:entity>
<prov:used>
	<prov:activity prov:ref="Process_5763"/>
	<prov:entity prov:ref="File_1105"/>
</prov:used>
<prov:entity prov:id="File_1108">
	<prov:value>Input</prov:value>
</prov:entity>
<prov:used>
	<prov:activity prov:ref="Process_5763"/>
	<prov:entity prov:ref="File_1108"/>
</prov:used>
<prov:entity prov:id="File_1109">
	<prov:value>Input</prov:value>
</prov:entity>
<prov:used>
	<prov:activity prov:ref="Process_5763"/>
	<prov:entity prov:ref="File_1109"/>
</prov:used>
<prov:entity prov:id="File_1111">
	<prov:value>Input</prov:value>
</prov:entity>
<prov:used>
	<prov:activity prov:ref="Process_5763"/>
	<prov:entity prov:ref="File_1111"/>
</prov:used>
<prov:entity prov:id="File_1113">
	<prov:value>Input</prov:value>
</prov:entity>
<prov:used>
	<prov:activity prov:ref="Process_5763"/>
	<prov:entity prov:ref="File_1113"/>
</prov:used>
<prov:entity prov:id="File_1115">
	<prov:value>Input</prov:value>
</prov:entity>
<prov:used>
	<prov:activity prov:ref="Process_5763"/>
	<prov:entity prov:ref="File_1115"/>
</prov:used>
<prov:entity prov:id="File_1117">
	<prov:value>Input</prov:value>
</prov:entity>
<prov:used>
	<prov:activity prov:ref="Process_5763"/>
	<prov:entity prov:ref="File_1117"/>
</prov:used>
<prov:entity prov:id="File_1119">
	<prov:value>Input</prov:value>
</prov:entity>
<prov:used>
	<prov:activity prov:ref="Process_5763"/>
	<prov:entity prov:ref="File_1119"/>
</prov:used>
<prov:entity prov:id="File_1121">
	<prov:value>Input</prov:value>
</prov:entity>
<prov:used>
	<prov:activity prov:ref="Process_5763"/>
	<prov:entity prov:ref="File_1121"/>
</prov:used>
<prov:entity prov:id="File_1123">
	<prov:value>Input</prov:value>
</prov:entity>
<prov:used>
	<prov:activity prov:ref="Process_5763"/>
	<prov:entity prov:ref="File_1123"/>
</prov:used>
<prov:entity prov:id="File_1125">
	<prov:value>Input</prov:value>
</prov:entity>
<prov:used>
	<prov:activity prov:ref="Process_5763"/>
	<prov:entity prov:ref="File_1125"/>
</prov:used>
<prov:entity prov:id="File_1127">
	<prov:value>Input</prov:value>
</prov:entity>
<prov:used>
	<prov:activity prov:ref="Process_5763"/>
	<prov:entity prov:ref="File_1127"/>
</prov:used>
<prov:entity prov:id="File_1129">
	<prov:value>Input</prov:value>
</prov:entity>
<prov:used>
	<prov:activity prov:ref="Process_5763"/>
	<prov:entity prov:ref="File_1129"/>
</prov:used>
<prov:entity prov:id="File_1131">
	<prov:value>Input</prov:value>
</prov:entity>
<prov:used>
	<prov:activity prov:ref="Process_5763"/>
	<prov:entity prov:ref="File_1131"/>
</prov:used>
<prov:entity prov:id="File_1133">
	<prov:value>Input</prov:value>
</prov:entity>
<prov:used>
	<prov:activity prov:ref="Process_5763"/>
	<prov:entity prov:ref="File_1133"/>
</prov:used>
<prov:entity prov:id="File_1135">
	<prov:value>Input</prov:value>
</prov:entity>
<prov:used>
	<prov:activity prov:ref="Process_5763"/>
	<prov:entity prov:ref="File_1135"/>
</prov:used>
<prov:entity prov:id="File_1137">
	<prov:value>Input</prov:value>
</prov:entity>
<prov:used>
	<prov:activity prov:ref="Process_5763"/>
	<prov:entity prov:ref="File_1137"/>
</prov:used>
<prov:entity prov:id="File_1139">
	<prov:value>Input</prov:value>
</prov:entity>
<prov:used>
	<prov:activity prov:ref="Process_5763"/>
	<prov:entity prov:ref="File_1139"/>
</prov:used>
<prov:entity prov:id="File_1141">
	<prov:value>Input</prov:value>
</prov:entity>
<prov:used>
	<prov:activity prov:ref="Process_5763"/>
	<prov:entity prov:ref="File_1141"/>
</prov:used>
<prov:entity prov:id="File_1143">
	<prov:value>Input</prov:value>
</prov:entity>
<prov:used>
	<prov:activity prov:ref="Process_5763"/>
	<prov:entity prov:ref="File_1143"/>
</prov:used>
<prov:entity prov:id="File_1145">
	<prov:value>Input</prov:value>
</prov:entity>
<prov:used>
	<prov:activity prov:ref="Process_5763"/>
	<prov:entity prov:ref="File_1145"/>
</prov:used>
<prov:entity prov:id="File_1148">
	<prov:value>Input</prov:value>
</prov:entity>
<prov:used>
	<prov:activity prov:ref="Process_5763"/>
	<prov:entity prov:ref="File_1148"/>
</prov:used>
<prov:entity prov:id="File_1149">
	<prov:value>Input</prov:value>
</prov:entity>
<prov:used>
	<prov:activity prov:ref="Process_5763"/>
	<prov:entity prov:ref="File_1149"/>
</prov:used>
<prov:entity prov:id="File_1151">
	<prov:value>Input</prov:value>
</prov:entity>
<prov:used>
	<prov:activity prov:ref="Process_5763"/>
	<prov:entity prov:ref="File_1151"/>
</prov:used>
<prov:entity prov:id="File_1153">
	<prov:value>Input</prov:value>
</prov:entity>
<prov:used>
	<prov:activity prov:ref="Process_5763"/>
	<prov:entity prov:ref="File_1153"/>
</prov:used>
<prov:entity prov:id="File_1155">
	<prov:value>Input</prov:value>
</prov:entity>
<prov:used>
	<prov:activity prov:ref="Process_5763"/>
	<prov:entity prov:ref="File_1155"/>
</prov:used>
<prov:entity prov:id="File_1157">
	<prov:value>Input</prov:value>
</prov:entity>
<prov:used>
	<prov:activity prov:ref="Process_5763"/>
	<prov:entity prov:ref="File_1157"/>
</prov:used>
<prov:entity prov:id="File_1159">
	<prov:value>Input</prov:value>
</prov:entity>
<prov:used>
	<prov:activity prov:ref="Process_5763"/>
	<prov:entity prov:ref="File_1159"/>
</prov:used>
<prov:entity prov:id="File_4303">
	<prov:value>Input</prov:value>
</prov:entity>
<prov:used>
	<prov:activity prov:ref="Process_5763"/>
	<prov:entity prov:ref="File_4303"/>
</prov:used>
<prov:activity prov:id="Process_5765">
	<prov:startTime>2011-10-12T00:43:04.000-04:00</prov:startTime>
	<prov:endTime>2011-10-12T00:43:04.000-04:00</prov:endTime>
</prov:activity>
<prov:entity prov:id="File_4318">
	<prov:value>Input</prov:value>
</prov:entity>
<prov:used>
	<prov:activity prov:ref="Process_5765"/>
	<prov:entity prov:ref="File_4318"/>
</prov:used>
<prov:entity prov:id="File_4319">
	<prov:value>Input</prov:value>
</prov:entity>
<prov:used>
	<prov:activity prov:ref="Process_5765"/>
	<prov:entity prov:ref="File_4319"/>
</prov:used>
<prov:entity prov:id="File_4320">
	<prov:value>Input</prov:value>
</prov:entity>
<prov:used>
	<prov:activity prov:ref="Process_5765"/>
	<prov:entity prov:ref="File_4320"/>
</prov:used>
<prov:activity prov:id="Process_5766">
	<prov:startTime>2011-10-12T00:43:10.000-04:00</prov:startTime>
	<prov:endTime>2011-10-12T00:43:10.000-04:00</prov:endTime>
</prov:activity>
<prov:entity prov:id="File_4324">
	<prov:value>Input</prov:value>
</prov:entity>
<prov:used>
	<prov:activity prov:ref="Process_5766"/>
	<prov:entity prov:ref="File_4324"/>
</prov:used>
<prov:entity prov:id="File_4325">
	<prov:value>Input</prov:value>
</prov:entity>
<prov:used>
	<prov:activity prov:ref="Process_5766"/>
	<prov:entity prov:ref="File_4325"/>
</prov:used>
<prov:entity prov:id="File_4326">
	<prov:value>Input</prov:value>
</prov:entity>
<prov:used>
	<prov:activity prov:ref="Process_5766"/>
	<prov:entity prov:ref="File_4326"/>
</prov:used>
<prov:entity prov:id="File_4327">
	<prov:value>Input</prov:value>
</prov:entity>
<prov:used>
	<prov:activity prov:ref="Process_5766"/>
	<prov:entity prov:ref="File_4327"/>
</prov:used>
<prov:entity prov:id="File_4328">
	<prov:value>Input</prov:value>
</prov:entity>
<prov:used>
	<prov:activity prov:ref="Process_5766"/>
	<prov:entity prov:ref="File_4328"/>
</prov:used>
<prov:entity prov:id="File_4329">
	<prov:value>Input</prov:value>
</prov:entity>
<prov:used>
	<prov:activity prov:ref="Process_5766"/>
	<prov:entity prov:ref="File_4329"/>
</prov:used>
<prov:entity prov:id="File_4330">
	<prov:value>Input</prov:value>
</prov:entity>
<prov:used>
	<prov:activity prov:ref="Process_5766"/>
	<prov:entity prov:ref="File_4330"/>
</prov:used>
<prov:entity prov:id="File_4331">
	<prov:value>Input</prov:value>
</prov:entity>
<prov:used>
	<prov:activity prov:ref="Process_5766"/>
	<prov:entity prov:ref="File_4331"/>
</prov:used>
<prov:entity prov:id="File_4332">
	<prov:value>Input</prov:value>
</prov:entity>
<prov:used>
	<prov:activity prov:ref="Process_5766"/>
	<prov:entity prov:ref="File_4332"/>
</prov:used>
<prov:entity prov:id="File_4333">
	<prov:value>Input</prov:value>
</prov:entity>
<prov:used>
	<prov:activity prov:ref="Process_5766"/>
	<prov:entity prov:ref="File_4333"/>
</prov:used>
<prov:wasDerivedFrom>
	<prov:generatedEntity prov:ref="File_4318"/>
	<prov:usedEntity prov:ref="File_1103"/>
</prov:wasDerivedFrom>
<prov:wasDerivedFrom>
	<prov:generatedEntity prov:ref="File_4318"/>
	<prov:usedEntity prov:ref="File_1105"/>
</prov:wasDerivedFrom>
<prov:wasDerivedFrom>
	<prov:generatedEntity prov:ref="File_4318"/>
	<prov:usedEntity prov:ref="File_1108"/>
</prov:wasDerivedFrom>
<prov:wasDerivedFrom>
	<prov:generatedEntity prov:ref="File_4318"/>
	<prov:usedEntity prov:ref="File_1109"/>
</prov:wasDerivedFrom>
<prov:wasDerivedFrom>
	<prov:generatedEntity prov:ref="File_4318"/>
	<prov:usedEntity prov:ref="File_1125"/>
</prov:wasDerivedFrom>
<prov:wasDerivedFrom>
	<prov:generatedEntity prov:ref="File_4318"/>
	<prov:usedEntity prov:ref="File_1111"/>
</prov:wasDerivedFrom>
<prov:wasDerivedFrom>
	<prov:generatedEntity prov:ref="File_4318"/>
	<prov:usedEntity prov:ref="File_1127"/>
</prov:wasDerivedFrom>
<prov:wasDerivedFrom>
	<prov:generatedEntity prov:ref="File_4318"/>
	<prov:usedEntity prov:ref="File_1129"/>
</prov:wasDerivedFrom>
<prov:wasDerivedFrom>
	<prov:generatedEntity prov:ref="File_4318"/>
	<prov:usedEntity prov:ref="File_1113"/>
</prov:wasDerivedFrom>
<prov:wasDerivedFrom>
	<prov:generatedEntity prov:ref="File_4318"/>
	<prov:usedEntity prov:ref="File_1131"/>
</prov:wasDerivedFrom>
<prov:wasDerivedFrom>
	<prov:generatedEntity prov:ref="File_4318"/>
	<prov:usedEntity prov:ref="File_1133"/>
</prov:wasDerivedFrom>
<prov:wasDerivedFrom>
	<prov:generatedEntity prov:ref="File_4318"/>
	<prov:usedEntity prov:ref="File_1115"/>
</prov:wasDerivedFrom>
<prov:wasDerivedFrom>
	<prov:generatedEntity prov:ref="File_4318"/>
	<prov:usedEntity prov:ref="File_1135"/>
</prov:wasDerivedFrom>
<prov:wasDerivedFrom>
	<prov:generatedEntity prov:ref="File_4318"/>
	<prov:usedEntity prov:ref="File_1117"/>
</prov:wasDerivedFrom>
<prov:wasDerivedFrom>
	<prov:generatedEntity prov:ref="File_4318"/>
	<prov:usedEntity prov:ref="File_1137"/>
</prov:wasDerivedFrom>
<prov:wasDerivedFrom>
	<prov:generatedEntity prov:ref="File_4318"/>
	<prov:usedEntity prov:ref="File_1119"/>
</prov:wasDerivedFrom>
<prov:wasDerivedFrom>
	<prov:generatedEntity prov:ref="File_4318"/>
	<prov:usedEntity prov:ref="File_1139"/>
</prov:wasDerivedFrom>
<prov:wasDerivedFrom>
	<prov:generatedEntity prov:ref="File_4318"/>
	<prov:usedEntity prov:ref="File_1121"/>
</prov:wasDerivedFrom>
<prov:wasDerivedFrom>
	<prov:generatedEntity prov:ref="File_4318"/>
	<prov:usedEntity prov:ref="File_1141"/>
</prov:wasDerivedFrom>
<prov:wasDerivedFrom>
	<prov:generatedEntity prov:ref="File_4318"/>
	<prov:usedEntity prov:ref="File_1123"/>
</prov:wasDerivedFrom>
<prov:wasDerivedFrom>
	<prov:generatedEntity prov:ref="File_4318"/>
	<prov:usedEntity prov:ref="File_1143"/>
</prov:wasDerivedFrom>
<prov:wasDerivedFrom>
	<prov:generatedEntity prov:ref="File_4318"/>
	<prov:usedEntity prov:ref="File_1145"/>
</prov:wasDerivedFrom>
<prov:wasDerivedFrom>
	<prov:generatedEntity prov:ref="File_4318"/>
	<prov:usedEntity prov:ref="File_1148"/>
</prov:wasDerivedFrom>
<prov:wasDerivedFrom>
	<prov:generatedEntity prov:ref="File_4318"/>
	<prov:usedEntity prov:ref="File_1149"/>
</prov:wasDerivedFrom>
<prov:wasDerivedFrom>
	<prov:generatedEntity prov:ref="File_4318"/>
	<prov:usedEntity prov:ref="File_1151"/>
</prov:wasDerivedFrom>
<prov:wasDerivedFrom>
	<prov:generatedEntity prov:ref="File_4318"/>
	<prov:usedEntity prov:ref="File_1153"/>
</prov:wasDerivedFrom>
<prov:wasDerivedFrom>
	<prov:generatedEntity prov:ref="File_4318"/>
	<prov:usedEntity prov:ref="File_1155"/>
</prov:wasDerivedFrom>
<prov:wasDerivedFrom>
	<prov:generatedEntity prov:ref="File_4318"/>
	<prov:usedEntity prov:ref="File_1157"/>
</prov:wasDerivedFrom>
<prov:wasDerivedFrom>
	<prov:generatedEntity prov:ref="File_4318"/>
	<prov:usedEntity prov:ref="File_1159"/>
</prov:wasDerivedFrom>
<prov:wasDerivedFrom>
	<prov:generatedEntity prov:ref="File_4318"/>
	<prov:usedEntity prov:ref="File_4303"/>
</prov:wasDerivedFrom>
<prov:wasDerivedFrom>
	<prov:generatedEntity prov:ref="File_4319"/>
	<prov:usedEntity prov:ref="File_1103"/>
</prov:wasDerivedFrom>
<prov:wasDerivedFrom>
	<prov:generatedEntity prov:ref="File_4319"/>
	<prov:usedEntity prov:ref="File_1105"/>
</prov:wasDerivedFrom>
<prov:wasDerivedFrom>
	<prov:generatedEntity prov:ref="File_4319"/>
	<prov:usedEntity prov:ref="File_1108"/>
</prov:wasDerivedFrom>
<prov:wasDerivedFrom>
	<prov:generatedEntity prov:ref="File_4319"/>
	<prov:usedEntity prov:ref="File_1109"/>
</prov:wasDerivedFrom>
<prov:wasDerivedFrom>
	<prov:generatedEntity prov:ref="File_4319"/>
	<prov:usedEntity prov:ref="File_1125"/>
</prov:wasDerivedFrom>
<prov:wasDerivedFrom>
	<prov:generatedEntity prov:ref="File_4319"/>
	<prov:usedEntity prov:ref="File_1111"/>
</prov:wasDerivedFrom>
<prov:wasDerivedFrom>
	<prov:generatedEntity prov:ref="File_4319"/>
	<prov:usedEntity prov:ref="File_1127"/>
</prov:wasDerivedFrom>
<prov:wasDerivedFrom>
	<prov:generatedEntity prov:ref="File_4319"/>
	<prov:usedEntity prov:ref="File_1129"/>
</prov:wasDerivedFrom>
<prov:wasDerivedFrom>
	<prov:generatedEntity prov:ref="File_4319"/>
	<prov:usedEntity prov:ref="File_1113"/>
</prov:wasDerivedFrom>
<prov:wasDerivedFrom>
	<prov:generatedEntity prov:ref="File_4319"/>
	<prov:usedEntity prov:ref="File_1131"/>
</prov:wasDerivedFrom>
<prov:wasDerivedFrom>
	<prov:generatedEntity prov:ref="File_4319"/>
	<prov:usedEntity prov:ref="File_1133"/>
</prov:wasDerivedFrom>
<prov:wasDerivedFrom>
	<prov:generatedEntity prov:ref="File_4319"/>
	<prov:usedEntity prov:ref="File_1115"/>
</prov:wasDerivedFrom>
<prov:wasDerivedFrom>
	<prov:generatedEntity prov:ref="File_4319"/>
	<prov:usedEntity prov:ref="File_1135"/>
</prov:wasDerivedFrom>
<prov:wasDerivedFrom>
	<prov:generatedEntity prov:ref="File_4319"/>
	<prov:usedEntity prov:ref="File_1117"/>
</prov:wasDerivedFrom>
<prov:wasDerivedFrom>
	<prov:generatedEntity prov:ref="File_4319"/>
	<prov:usedEntity prov:ref="File_1137"/>
</prov:wasDerivedFrom>
<prov:wasDerivedFrom>
	<prov:generatedEntity prov:ref="File_4319"/>
	<prov:usedEntity prov:ref="File_1119"/>
</prov:wasDerivedFrom>
<prov:wasDerivedFrom>
	<prov:generatedEntity prov:ref="File_4319"/>
	<prov:usedEntity prov:ref="File_1139"/>
</prov:wasDerivedFrom>
<prov:wasDerivedFrom>
	<prov:generatedEntity prov:ref="File_4319"/>
	<prov:usedEntity prov:ref="File_1121"/>
</prov:wasDerivedFrom>
<prov:wasDerivedFrom>
	<prov:generatedEntity prov:ref="File_4319"/>
	<prov:usedEntity prov:ref="File_1141"/>
</prov:wasDerivedFrom>
<prov:wasDerivedFrom>
	<prov:generatedEntity prov:ref="File_4319"/>
	<prov:usedEntity prov:ref="File_1123"/>
</prov:wasDerivedFrom>
<prov:wasDerivedFrom>
	<prov:generatedEntity prov:ref="File_4319"/>
	<prov:usedEntity prov:ref="File_1143"/>
</prov:wasDerivedFrom>
<prov:wasDerivedFrom>
	<prov:generatedEntity prov:ref="File_4319"/>
	<prov:usedEntity prov:ref="File_1145"/>
</prov:wasDerivedFrom>
<prov:wasDerivedFrom>
	<prov:generatedEntity prov:ref="File_4319"/>
	<prov:usedEntity prov:ref="File_1148"/>
</prov:wasDerivedFrom>
<prov:wasDerivedFrom>
	<prov:generatedEntity prov:ref="File_4319"/>
	<prov:usedEntity prov:ref="File_1149"/>
</prov:wasDerivedFrom>
<prov:wasDerivedFrom>
	<prov:generatedEntity prov:ref="File_4319"/>
	<prov:usedEntity prov:ref="File_1151"/>
</prov:wasDerivedFrom>
<prov:wasDerivedFrom>
	<prov:generatedEntity prov:ref="File_4319"/>
	<prov:usedEntity prov:ref="File_1153"/>
</prov:wasDerivedFrom>
<prov:wasDerivedFrom>
	<prov:generatedEntity prov:ref="File_4319"/>
	<prov:usedEntity prov:ref="File_1155"/>
</prov:wasDerivedFrom>
<prov:wasDerivedFrom>
	<prov:generatedEntity prov:ref="File_4319"/>
	<prov:usedEntity prov:ref="File_1157"/>
</prov:wasDerivedFrom>
<prov:wasDerivedFrom>
	<prov:generatedEntity prov:ref="File_4319"/>
	<prov:usedEntity prov:ref="File_1159"/>
</prov:wasDerivedFrom>
<prov:wasDerivedFrom>
	<prov:generatedEntity prov:ref="File_4319"/>
	<prov:usedEntity prov:ref="File_4303"/>
</prov:wasDerivedFrom>
<prov:wasDerivedFrom>
	<prov:generatedEntity prov:ref="File_4320"/>
	<prov:usedEntity prov:ref="File_1103"/>
</prov:wasDerivedFrom>
<prov:wasDerivedFrom>
	<prov:generatedEntity prov:ref="File_4320"/>
	<prov:usedEntity prov:ref="File_1105"/>
</prov:wasDerivedFrom>
<prov:wasDerivedFrom>
	<prov:generatedEntity prov:ref="File_4320"/>
	<prov:usedEntity prov:ref="File_1108"/>
</prov:wasDerivedFrom>
<prov:wasDerivedFrom>
	<prov:generatedEntity prov:ref="File_4320"/>
	<prov:usedEntity prov:ref="File_1109"/>
</prov:wasDerivedFrom>
<prov:wasDerivedFrom>
	<prov:generatedEntity prov:ref="File_4320"/>
	<prov:usedEntity prov:ref="File_1125"/>
</prov:wasDerivedFrom>
<prov:wasDerivedFrom>
	<prov:generatedEntity prov:ref="File_4320"/>
	<prov:usedEntity prov:ref="File_1111"/>
</prov:wasDerivedFrom>
<prov:wasDerivedFrom>
	<prov:generatedEntity prov:ref="File_4320"/>
	<prov:usedEntity prov:ref="File_1127"/>
</prov:wasDerivedFrom>
<prov:wasDerivedFrom>
	<prov:generatedEntity prov:ref="File_4320"/>
	<prov:usedEntity prov:ref="File_1129"/>
</prov:wasDerivedFrom>
<prov:wasDerivedFrom>
	<prov:generatedEntity prov:ref="File_4320"/>
	<prov:usedEntity prov:ref="File_1113"/>
</prov:wasDerivedFrom>
<prov:wasDerivedFrom>
	<prov:generatedEntity prov:ref="File_4320"/>
	<prov:usedEntity prov:ref="File_1131"/>
</prov:wasDerivedFrom>
<prov:wasDerivedFrom>
	<prov:generatedEntity prov:ref="File_4320"/>
	<prov:usedEntity prov:ref="File_1133"/>
</prov:wasDerivedFrom>
<prov:wasDerivedFrom>
	<prov:generatedEntity prov:ref="File_4320"/>
	<prov:usedEntity prov:ref="File_1115"/>
</prov:wasDerivedFrom>
<prov:wasDerivedFrom>
	<prov:generatedEntity prov:ref="File_4320"/>
	<prov:usedEntity prov:ref="File_1135"/>
</prov:wasDerivedFrom>
<prov:wasDerivedFrom>
	<prov:generatedEntity prov:ref="File_4320"/>
	<prov:usedEntity prov:ref="File_1117"/>
</prov:wasDerivedFrom>
<prov:wasDerivedFrom>
	<prov:generatedEntity prov:ref="File_4320"/>
	<prov:usedEntity prov:ref="File_1137"/>
</prov:wasDerivedFrom>
<prov:wasDerivedFrom>
	<prov:generatedEntity prov:ref="File_4320"/>
	<prov:usedEntity prov:ref="File_1119"/>
</prov:wasDerivedFrom>
<prov:wasDerivedFrom>
	<prov:generatedEntity prov:ref="File_4320"/>
	<prov:usedEntity prov:ref="File_1139"/>
</prov:wasDerivedFrom>
<prov:wasDerivedFrom>
	<prov:generatedEntity prov:ref="File_4320"/>
	<prov:usedEntity prov:ref="File_1121"/>
</prov:wasDerivedFrom>
<prov:wasDerivedFrom>
	<prov:generatedEntity prov:ref="File_4320"/>
	<prov:usedEntity prov:ref="File_1141"/>
</prov:wasDerivedFrom>
<prov:wasDerivedFrom>
	<prov:generatedEntity prov:ref="File_4320"/>
	<prov:usedEntity prov:ref="File_1123"/>
</prov:wasDerivedFrom>
<prov:wasDerivedFrom>
	<prov:generatedEntity prov:ref="File_4320"/>
	<prov:usedEntity prov:ref="File_1143"/>
</prov:wasDerivedFrom>
<prov:wasDerivedFrom>
	<prov:generatedEntity prov:ref="File_4320"/>
	<prov:usedEntity prov:ref="File_1145"/>
</prov:wasDerivedFrom>
<prov:wasDerivedFrom>
	<prov:generatedEntity prov:ref="File_4320"/>
	<prov:usedEntity prov:ref="File_1148"/>
</prov:wasDerivedFrom>
<prov:wasDerivedFrom>
	<prov:generatedEntity prov:ref="File_4320"/>
	<prov:usedEntity prov:ref="File_1149"/>
</prov:wasDerivedFrom>
<prov:wasDerivedFrom>
	<prov:generatedEntity prov:ref="File_4320"/>
	<prov:usedEntity prov:ref="File_1151"/>
</prov:wasDerivedFrom>
<prov:wasDerivedFrom>
	<prov:generatedEntity prov:ref="File_4320"/>
	<prov:usedEntity prov:ref="File_1153"/>
</prov:wasDerivedFrom>
<prov:wasDerivedFrom>
	<prov:generatedEntity prov:ref="File_4320"/>
	<prov:usedEntity prov:ref="File_1155"/>
</prov:wasDerivedFrom>
<prov:wasDerivedFrom>
	<prov:generatedEntity prov:ref="File_4320"/>
	<prov:usedEntity prov:ref="File_1157"/>
</prov:wasDerivedFrom>
<prov:wasDerivedFrom>
	<prov:generatedEntity prov:ref="File_4320"/>
	<prov:usedEntity prov:ref="File_1159"/>
</prov:wasDerivedFrom>
<prov:wasDerivedFrom>
	<prov:generatedEntity prov:ref="File_4320"/>
	<prov:usedEntity prov:ref="File_4303"/>
</prov:wasDerivedFrom>
<prov:entity prov:id="File_4321">
</prov:entity>
<prov:wasDerivedFrom>
	<prov:generatedEntity prov:ref="File_4321"/>
	<prov:usedEntity prov:ref="File_4324"/>
</prov:wasDerivedFrom>
<prov:wasDerivedFrom>
	<prov:generatedEntity prov:ref="File_4321"/>
	<prov:usedEntity prov:ref="File_4325"/>
</prov:wasDerivedFrom>
<prov:wasDerivedFrom>
	<prov:generatedEntity prov:ref="File_4321"/>
	<prov:usedEntity prov:ref="File_4326"/>
</prov:wasDerivedFrom>
<prov:wasDerivedFrom>
	<prov:generatedEntity prov:ref="File_4321"/>
	<prov:usedEntity prov:ref="File_4327"/>
</prov:wasDerivedFrom>
<prov:wasDerivedFrom>
	<prov:generatedEntity prov:ref="File_4321"/>
	<prov:usedEntity prov:ref="File_4328"/>
</prov:wasDerivedFrom>
<prov:wasDerivedFrom>
	<prov:generatedEntity prov:ref="File_4321"/>
	<prov:usedEntity prov:ref="File_4329"/>
</prov:wasDerivedFrom>
<prov:wasDerivedFrom>
	<prov:generatedEntity prov:ref="File_4321"/>
	<prov:usedEntity prov:ref="File_4330"/>
</prov:wasDerivedFrom>
<prov:wasDerivedFrom>
	<prov:generatedEntity prov:ref="File_4321"/>
	<prov:usedEntity prov:ref="File_4331"/>
</prov:wasDerivedFrom>
<prov:wasDerivedFrom>
	<prov:generatedEntity prov:ref="File_4321"/>
	<prov:usedEntity prov:ref="File_4332"/>
</prov:wasDerivedFrom>
<prov:wasDerivedFrom>
	<prov:generatedEntity prov:ref="File_4321"/>
	<prov:usedEntity prov:ref="File_4333"/>
</prov:wasDerivedFrom>
<prov:entity prov:id="File_4322">
</prov:entity>
<prov:wasDerivedFrom>
	<prov:generatedEntity prov:ref="File_4322"/>
	<prov:usedEntity prov:ref="File_4324"/>
</prov:wasDerivedFrom>
<prov:wasDerivedFrom>
	<prov:generatedEntity prov:ref="File_4322"/>
	<prov:usedEntity prov:ref="File_4325"/>
</prov:wasDerivedFrom>
<prov:wasDerivedFrom>
	<prov:generatedEntity prov:ref="File_4322"/>
	<prov:usedEntity prov:ref="File_4326"/>
</prov:wasDerivedFrom>
<prov:wasDerivedFrom>
	<prov:generatedEntity prov:ref="File_4322"/>
	<prov:usedEntity prov:ref="File_4327"/>
</prov:wasDerivedFrom>
<prov:wasDerivedFrom>
	<prov:generatedEntity prov:ref="File_4322"/>
	<prov:usedEntity prov:ref="File_4328"/>
</prov:wasDerivedFrom>
<prov:wasDerivedFrom>
	<prov:generatedEntity prov:ref="File_4322"/>
	<prov:usedEntity prov:ref="File_4329"/>
</prov:wasDerivedFrom>
<prov:wasDerivedFrom>
	<prov:generatedEntity prov:ref="File_4322"/>
	<prov:usedEntity prov:ref="File_4330"/>
</prov:wasDerivedFrom>
<prov:wasDerivedFrom>
	<prov:generatedEntity prov:ref="File_4322"/>
	<prov:usedEntity prov:ref="File_4331"/>
</prov:wasDerivedFrom>
<prov:wasDerivedFrom>
	<prov:generatedEntity prov:ref="File_4322"/>
	<prov:usedEntity prov:ref="File_4332"/>
</prov:wasDerivedFrom>
<prov:wasDerivedFrom>
	<prov:generatedEntity prov:ref="File_4322"/>
	<prov:usedEntity prov:ref="File_4333"/>
</prov:wasDerivedFrom>
<prov:entity prov:id="File_4323">
</prov:entity>
<prov:wasDerivedFrom>
	<prov:generatedEntity prov:ref="File_4323"/>
	<prov:usedEntity prov:ref="File_4324"/>
</prov:wasDerivedFrom>
<prov:wasDerivedFrom>
	<prov:generatedEntity prov:ref="File_4323"/>
	<prov:usedEntity prov:ref="File_4325"/>
</prov:wasDerivedFrom>
<prov:wasDerivedFrom>
	<prov:generatedEntity prov:ref="File_4323"/>
	<prov:usedEntity prov:ref="File_4326"/>
</prov:wasDerivedFrom>
<prov:wasDerivedFrom>
	<prov:generatedEntity prov:ref="File_4323"/>
	<prov:usedEntity prov:ref="File_4327"/>
</prov:wasDerivedFrom>
<prov:wasDerivedFrom>
	<prov:generatedEntity prov:ref="File_4323"/>
	<prov:usedEntity prov:ref="File_4328"/>
</prov:wasDerivedFrom>
<prov:wasDerivedFrom>
	<prov:generatedEntity prov:ref="File_4323"/>
	<prov:usedEntity prov:ref="File_4329"/>
</prov:wasDerivedFrom>
<prov:wasDerivedFrom>
	<prov:generatedEntity prov:ref="File_4323"/>
	<prov:usedEntity prov:ref="File_4330"/>
</prov:wasDerivedFrom>
<prov:wasDerivedFrom>
	<prov:generatedEntity prov:ref="File_4323"/>
	<prov:usedEntity prov:ref="File_4331"/>
</prov:wasDerivedFrom>
<prov:wasDerivedFrom>
	<prov:generatedEntity prov:ref="File_4323"/>
	<prov:usedEntity prov:ref="File_4332"/>
</prov:wasDerivedFrom>
<prov:wasDerivedFrom>
	<prov:generatedEntity prov:ref="File_4323"/>
	<prov:usedEntity prov:ref="File_4333"/>
</prov:wasDerivedFrom>
<prov:wasInformedBy>
	<prov:informed prov:ref="Process_5765"/>
	<prov:informant prov:ref="Process_5763"/>
</prov:wasInformedBy>
<prov:wasInformedBy>
	<prov:informed prov:ref="Process_5765"/>
	<prov:informant prov:ref="Process_5763"/>
</prov:wasInformedBy>
<prov:wasInformedBy>
	<prov:informed prov:ref="Process_5765"/>
	<prov:informant prov:ref="Process_5763"/>
</prov:wasInformedBy>
<prov:activity prov:id="Process_5764">
	<prov:startTime>2011-10-12T00:33:28.000-04:00</prov:startTime>
	<prov:endTime>2011-10-12T00:33:28.000-04:00</prov:endTime>
</prov:activity>
<prov:wasInformedBy>
	<prov:informed prov:ref="Process_5763"/>
	<prov:informant prov:ref="Process_5764"/>
</prov:wasInformedBy>
<prov:wasInformedBy>
	<prov:informed prov:ref="Process_5765"/>
	<prov:informant prov:ref="Process_5764"/>
</prov:wasInformedBy>
<prov:wasInformedBy>
	<prov:informed prov:ref="Process_5766"/>
	<prov:informant prov:ref="Process_5764"/>
</prov:wasInformedBy>
<prov:wasGeneratedBy>
	<prov:entity prov:ref="File_4318"/>
	<prov:activity prov:ref="Process_5763"/>
	<prov:role>Output</prov:role>
</prov:wasGeneratedBy>
<prov:wasGeneratedBy>
	<prov:entity prov:ref="File_4319"/>
	<prov:activity prov:ref="Process_5763"/>
	<prov:role>Output</prov:role>
</prov:wasGeneratedBy>
<prov:wasGeneratedBy>
	<prov:entity prov:ref="File_4320"/>
	<prov:activity prov:ref="Process_5763"/>
	<prov:role>Output</prov:role>
</prov:wasGeneratedBy>
<prov:wasGeneratedBy>
	<prov:entity prov:ref="File_4321"/>
	<prov:activity prov:ref="Process_5766"/>
	<prov:role>Output</prov:role>
</prov:wasGeneratedBy>
<prov:wasGeneratedBy>
	<prov:entity prov:ref="File_4322"/>
	<prov:activity prov:ref="Process_5766"/>
	<prov:role>Output</prov:role>
</prov:wasGeneratedBy>
<prov:wasGeneratedBy>
	<prov:entity prov:ref="File_4323"/>
	<prov:activity prov:ref="Process_5766"/>
	<prov:role>Output</prov:role>
</prov:wasGeneratedBy>
</prov:document>